fynx/__init__.py
fynx/observable/__init__.py
fynx/observable/base.py
fynx/observable/computed.py
fynx/observable/conditional.py
fynx/observable/descriptors.py
fynx/observable/interfaces.py
fynx/observable/merged.py
fynx/observable/operations.py
fynx/observable/operators.py
fynx/optimizer/__init__.py
fynx/optimizer/dependency_graph.py
fynx/optimizer/dependency_node.py
fynx/optimizer/morphism.py
fynx/optimizer/optimizer.py
fynx/optimizer/reactive_graph.py
fynx/reactive.py
fynx/registry.py
fynx/store.py
fynx-0.1.2.dist-info/METADATA
fynx-0.1.2.dist-info/WHEEL
fynx-0.1.2.dist-info/licenses/LICENSE
fynx-0.1.2.dist-info/RECORD
