Metadata-Version: 2.4
Name: fynx
Version: 0.1.2
Summary: Python reactive state management library inspired by MobX
License: MIT
License-File: LICENSE
Keywords: reactive,state-management,observable,functional-programming,mobx
Author: Cassidy Bridges
Author-email: cassidybridges@gmail.com
Requires-Python: >=3.9
Classifier: Development Status :: 3 - Alpha
Classifier: Intended Audience :: Developers
Classifier: License :: OSI Approved :: MIT License
Classifier: Operating System :: OS Independent
Classifier: Programming Language :: Python :: 3
Classifier: Programming Language :: Python :: 3.9
Classifier: Programming Language :: Python :: 3.10
Classifier: Programming Language :: Python :: 3.11
Classifier: Programming Language :: Python :: 3.12
Classifier: Programming Language :: Python :: 3.13
Classifier: Programming Language :: Python :: 3.14
Classifier: Topic :: Software Development :: Libraries :: Python Modules
Classifier: Topic :: Utilities
Project-URL: Homepage, https://github.com/off-by-some/fynx
Project-URL: Repository, https://github.com/off-by-some/fynx
